{
 "custom_fields": [
  {
   "_assign": null,
   "_comments": null,
   "_liked_by": null,
   "_user_tags": null,
   "allow_on_submit": 0,
   "bold": 0,
   "collapsible": 1,
   "collapsible_depends_on": null,
   "columns": 0,
   "creation": "2018-01-11 17:27:50.303685",
   "default": null,
   "depends_on": null,
   "description": null,
   "docstatus": 0,
   "dt": "Item",
   "fetch_from": null,
   "fetch_if_empty": 0,
   "fieldname": "sb90",
   "fieldtype": "Section Break",
   "hidden": 0,
   "idx": 29,
   "ignore_user_permissions": 0,
   "ignore_xss_filter": 0,
   "in_global_search": 0,
   "in_list_view": 0,
   "in_standard_filter": 0,
   "insert_after": "repair_item_specification",
   "label": "Repair Item Specification",
   "modified": "2018-01-11 17:27:50.303685",
   "modified_by": "Administrator",
   "name": "Item-sb90",
   "no_copy": 0,
   "options": null,
   "owner": "Administrator",
   "parent": null,
   "parentfield": null,
   "parenttype": null,
   "permlevel": 0,
   "precision": "",
   "print_hide": 0,
   "print_hide_if_no_value": 0,
   "print_width": null,
   "read_only": 0,
   "report_hide": 0,
   "reqd": 0,
   "search_index": 0,
   "translatable": 1,
   "unique": 0,
   "width": null
  },
  {
   "_assign": null,
   "_comments": null,
   "_liked_by": null,
   "_user_tags": null,
   "allow_on_submit": 0,
   "bold": 0,
   "collapsible": 0,
   "collapsible_depends_on": null,
   "columns": 0,
   "creation": "2019-08-29 08:50:05.151392",
   "default": null,
   "depends_on": null,
   "description": null,
   "docstatus": 0,
   "dt": "Item",
   "fetch_from": null,
   "fetch_if_empty": 0,
   "fieldname": "hub_sync_id",
   "fieldtype": "Data",
   "hidden": 1,
   "idx": 1,
   "ignore_user_permissions": 0,
   "ignore_xss_filter": 0,
   "in_global_search": 0,
   "in_list_view": 0,
   "in_standard_filter": 0,
   "insert_after": null,
   "label": "Hub Sync ID",
   "modified": "2019-08-29 08:50:05.151392",
   "modified_by": "Administrator",
   "name": "Item-hub_sync_id",
   "no_copy": 1,
   "options": null,
   "owner": "Administrator",
   "parent": null,
   "parentfield": null,
   "parenttype": null,
   "permlevel": 0,
   "precision": null,
   "print_hide": 0,
   "print_hide_if_no_value": 0,
   "print_width": null,
   "read_only": 1,
   "report_hide": 0,
   "reqd": 0,
   "search_index": 0,
   "translatable": 0,
   "unique": 1,
   "width": null
  },
  {
   "_assign": null,
   "_comments": null,
   "_liked_by": null,
   "_user_tags": null,
   "allow_on_submit": 0,
   "bold": 0,
   "collapsible": 0,
   "collapsible_depends_on": null,
   "columns": 0,
   "creation": "2019-08-29 09:05:35.212292",
   "default": null,
   "depends_on": null,
   "description": null,
   "docstatus": 0,
   "dt": "Item",
   "fetch_from": null,
   "fetch_if_empty": 0,
   "fieldname": "gst_hsn_code",
   "fieldtype": "Link",
   "hidden": 0,
   "idx": 8,
   "ignore_user_permissions": 0,
   "ignore_xss_filter": 0,
   "in_global_search": 0,
   "in_list_view": 0,
   "in_standard_filter": 0,
   "insert_after": "item_group",
   "label": "HSN/SAC",
   "modified": "2019-08-29 09:05:35.212292",
   "modified_by": "Administrator",
   "name": "Item-gst_hsn_code",
   "no_copy": 0,
   "options": "GST HSN Code",
   "owner": "Administrator",
   "parent": null,
   "parentfield": null,
   "parenttype": null,
   "permlevel": 0,
   "precision": "",
   "print_hide": 0,
   "print_hide_if_no_value": 0,
   "print_width": null,
   "read_only": 0,
   "report_hide": 0,
   "reqd": 0,
   "search_index": 0,
   "translatable": 0,
   "unique": 0,
   "width": null
  },
  {
   "_assign": null,
   "_comments": null,
   "_liked_by": null,
   "_user_tags": null,
   "allow_on_submit": 0,
   "bold": 0,
   "collapsible": 0,
   "collapsible_depends_on": null,
   "columns": 0,
   "creation": "2019-08-29 09:05:35.651335",
   "default": null,
   "depends_on": null,
   "description": null,
   "docstatus": 0,
   "dt": "Item",
   "fetch_from": null,
   "fetch_if_empty": 0,
   "fieldname": "is_nil_exempt",
   "fieldtype": "Check",
   "hidden": 0,
   "idx": 9,
   "ignore_user_permissions": 0,
   "ignore_xss_filter": 0,
   "in_global_search": 0,
   "in_list_view": 0,
   "in_standard_filter": 0,
   "insert_after": "gst_hsn_code",
   "label": "Is nil rated or exempted",
   "modified": "2019-08-29 09:05:35.651335",
   "modified_by": "Administrator",
   "name": "Item-is_nil_exempt",
   "no_copy": 0,
   "options": null,
   "owner": "Administrator",
   "parent": null,
   "parentfield": null,
   "parenttype": null,
   "permlevel": 0,
   "precision": "",
   "print_hide": 0,
   "print_hide_if_no_value": 0,
   "print_width": null,
   "read_only": 0,
   "report_hide": 0,
   "reqd": 0,
   "search_index": 0,
   "translatable": 0,
   "unique": 0,
   "width": null
  },
  {
   "_assign": null,
   "_comments": null,
   "_liked_by": null,
   "_user_tags": null,
   "allow_on_submit": 0,
   "bold": 0,
   "collapsible": 0,
   "collapsible_depends_on": null,
   "columns": 0,
   "creation": "2019-08-29 09:05:36.083628",
   "default": null,
   "depends_on": null,
   "description": null,
   "docstatus": 0,
   "dt": "Item",
   "fetch_from": null,
   "fetch_if_empty": 0,
   "fieldname": "is_non_gst",
   "fieldtype": "Check",
   "hidden": 0,
   "idx": 10,
   "ignore_user_permissions": 0,
   "ignore_xss_filter": 0,
   "in_global_search": 0,
   "in_list_view": 0,
   "in_standard_filter": 0,
   "insert_after": "is_nil_exempt",
   "label": "Is Non GST ",
   "modified": "2019-08-29 09:05:36.083628",
   "modified_by": "Administrator",
   "name": "Item-is_non_gst",
   "no_copy": 0,
   "options": null,
   "owner": "Administrator",
   "parent": null,
   "parentfield": null,
   "parenttype": null,
   "permlevel": 0,
   "precision": "",
   "print_hide": 0,
   "print_hide_if_no_value": 0,
   "print_width": null,
   "read_only": 0,
   "report_hide": 0,
   "reqd": 0,
   "search_index": 0,
   "translatable": 0,
   "unique": 0,
   "width": null
  },
  {
   "_assign": null,
   "_comments": null,
   "_liked_by": null,
   "_user_tags": null,
   "allow_on_submit": 0,
   "bold": 0,
   "collapsible": 0,
   "collapsible_depends_on": null,
   "columns": 0,
   "creation": "2019-08-29 10:39:22.975400",
   "default": null,
   "depends_on": null,
   "description": null,
   "docstatus": 0,
   "dt": "Item",
   "fetch_from": null,
   "fetch_if_empty": 0,
   "fieldname": "upremark",
   "fieldtype": "Data",
   "hidden": 0,
   "idx": 135,
   "ignore_user_permissions": 0,
   "ignore_xss_filter": 0,
   "in_global_search": 0,
   "in_list_view": 0,
   "in_standard_filter": 0,
   "insert_after": "manufacturers",
   "label": "UpRemark",
   "modified": "2019-08-29 10:39:22.975400",
   "modified_by": "ashish@greycube.in",
   "name": "Item-upremark",
   "no_copy": 0,
   "options": null,
   "owner": "ashish@greycube.in",
   "parent": null,
   "parentfield": null,
   "parenttype": null,
   "permlevel": 0,
   "precision": "",
   "print_hide": 0,
   "print_hide_if_no_value": 0,
   "print_width": null,
   "read_only": 0,
   "report_hide": 0,
   "reqd": 0,
   "search_index": 0,
   "translatable": 1,
   "unique": 0,
   "width": null
  },
  {
   "_assign": null,
   "_comments": null,
   "_liked_by": null,
   "_user_tags": null,
   "allow_on_submit": 0,
   "bold": 0,
   "collapsible": 0,
   "collapsible_depends_on": null,
   "columns": 0,
   "creation": "2019-08-29 10:42:35.814097",
   "default": null,
   "depends_on": null,
   "description": null,
   "docstatus": 0,
   "dt": "Item",
   "fetch_from": null,
   "fetch_if_empty": 0,
   "fieldname": "repair_item_section",
   "fieldtype": "Section Break",
   "hidden": 0,
   "idx": 27,
   "ignore_user_permissions": 0,
   "ignore_xss_filter": 0,
   "in_global_search": 0,
   "in_list_view": 0,
   "in_standard_filter": 0,
   "insert_after": "image",
   "label": "repair_item_section",
   "modified": "2019-08-29 10:42:35.814097",
   "modified_by": "ashish@greycube.in",
   "name": "Item-repair_item_section",
   "no_copy": 0,
   "options": null,
   "owner": "Administrator",
   "parent": null,
   "parentfield": null,
   "parenttype": null,
   "permlevel": 0,
   "precision": "",
   "print_hide": 0,
   "print_hide_if_no_value": 0,
   "print_width": null,
   "read_only": 0,
   "report_hide": 0,
   "reqd": 0,
   "search_index": 0,
   "translatable": 0,
   "unique": 0,
   "width": null
  },
  {
   "_assign": null,
   "_comments": null,
   "_liked_by": null,
   "_user_tags": null,
   "allow_on_submit": 0,
   "bold": 0,
   "collapsible": 0,
   "collapsible_depends_on": null,
   "columns": 0,
   "creation": "2019-08-29 10:42:36.216484",
   "default": null,
   "depends_on": null,
   "description": null,
   "docstatus": 0,
   "dt": "Item",
   "fetch_from": null,
   "fetch_if_empty": 0,
   "fieldname": "repair_item_specification",
   "fieldtype": "Table",
   "hidden": 0,
   "idx": 28,
   "ignore_user_permissions": 0,
   "ignore_xss_filter": 0,
   "in_global_search": 0,
   "in_list_view": 0,
   "in_standard_filter": 0,
   "insert_after": "repair_item_section",
   "label": "repair_item_specification",
   "modified": "2019-08-29 10:42:36.216484",
   "modified_by": "ashish@greycube.in",
   "name": "Item-repair_item_specification",
   "no_copy": 0,
   "options": "Repair Item Specification",
   "owner": "ashish@greycube.in",
   "parent": null,
   "parentfield": null,
   "parenttype": null,
   "permlevel": 0,
   "precision": "",
   "print_hide": 0,
   "print_hide_if_no_value": 0,
   "print_width": null,
   "read_only": 0,
   "report_hide": 0,
   "reqd": 0,
   "search_index": 0,
   "translatable": 0,
   "unique": 0,
   "width": null
  },
  {
   "_assign": null,
   "_comments": null,
   "_liked_by": null,
   "_user_tags": null,
   "allow_on_submit": 0,
   "bold": 0,
   "collapsible": 0,
   "collapsible_depends_on": "",
   "columns": 0,
   "creation": "2019-10-24 08:04:30.800154",
   "default": null,
   "depends_on": "",
   "description": null,
   "docstatus": 0,
   "dt": "Item",
   "fetch_from": null,
   "fetch_if_empty": 0,
   "fieldname": "website_title_qr",
   "fieldtype": "Data",
   "hidden": 0,
   "idx": 122,
   "ignore_user_permissions": 0,
   "ignore_xss_filter": 0,
   "in_global_search": 0,
   "in_list_view": 0,
   "in_standard_filter": 0,
   "insert_after": "set_meta_tags",
   "label": "Website Title QR",
   "modified": "2019-10-24 08:04:30.800154",
   "modified_by": "Administrator",
   "name": "Item-website_title_qr",
   "no_copy": 0,
   "options": null,
   "owner": "Administrator",
   "parent": null,
   "parentfield": null,
   "parenttype": null,
   "permlevel": 0,
   "precision": "",
   "print_hide": 0,
   "print_hide_if_no_value": 0,
   "print_width": null,
   "read_only": 0,
   "report_hide": 0,
   "reqd": 0,
   "search_index": 0,
   "translatable": 0,
   "unique": 0,
   "width": null
  }
 ],
 "custom_perms": [],
 "doctype": "Item",
 "property_setters": [],
 "sync_on_migrate": 1
}